django_materialized_view/__init__.py
django_materialized_view/apps.py
django_materialized_view/base_model.py
django_materialized_view/models.py
django_materialized_view/processor.py
django_materialized_view/sql_functions.py
django_materialized_view/management/__init__.py
django_materialized_view/management/commands/__init__.py
django_materialized_view/management/commands/migrate_with_views.py
django_materialized_view/migrations/0001_initial.py
django_materialized_view/migrations/__init__.py
testproject/__init__.py
testproject/manage.py
testproject/settings.py
testproject/urls.py
testproject/tests/__init__.py
testproject/tests/factories.py
testproject/tests/test_base_mode_tests.py
testproject/tests/management/__init__.py
testproject/tests/management/commands/__init__.py
testproject/tests/management/commands/test_migrate_with_views.py
django_materialized_view-0.1.6.2.dist-info/LICENSE
django_materialized_view-0.1.6.2.dist-info/METADATA
django_materialized_view-0.1.6.2.dist-info/WHEEL
django_materialized_view-0.1.6.2.dist-info/top_level.txt
django_materialized_view-0.1.6.2.dist-info/RECORD
