Metadata-Version: 2.1
Name: django-materialized-view
Version: 0.1.6.2
Summary: Plugin for django to support Materialized Views
Home-page: https://github.com/muehlemann-popp/django-materialized-view
Author: Farruh Sheripiov
Author-email: farruh.sheripov@muehlemann-popp.ch
Maintainer: Silvan Mühlemann
Maintainer-email: silvan.muehlemann@muehlemann-popp.ch
License: 'MIT'
Classifier: Intended Audience :: Developers
Classifier: Development Status :: 5 - Production/Stable
Classifier: License :: OSI Approved :: MIT License
Classifier: Operating System :: OS Independent
Classifier: Topic :: Software Development
Classifier: Framework :: Django
Classifier: Framework :: Django :: 4.0
Classifier: Framework :: Django :: 4.1
Classifier: Programming Language :: Python
Classifier: Programming Language :: Python :: 3.8
Classifier: Programming Language :: Python :: 3.9
Classifier: Programming Language :: Python :: 3.10
Classifier: Programming Language :: Python :: 3.11
Requires-Python: >=3.8
License-File: LICENSE
Requires-Dist: Django >=4.0
